Metadata-Version: 1.0
Name: megaomx
Version: 0.2
Summary: The omx series control
Home-page: https://github.com/megarobo-open/omx.git
Author: well4u
Author-email: wellau@qq.com
License: MIT
Keywords: megarobo om ovl
Platform: UNKNOWN
